imap_pydantic_client/__init__.py
imap_pydantic_client/client.py
imap_pydantic_client/constans.py
imap_pydantic_client/decoder/__init__.py
imap_pydantic_client/decoder/constants.py
imap_pydantic_client/decoder/processors.py
imap_pydantic_client/decoder/structs.py
imap_pydantic_client/factorys/__init__.py
imap_pydantic_client/factorys/content.py
imap_pydantic_client/factorys/email_message.py
imap_pydantic_client/factorys/fakers.py
imap_pydantic_client/factorys/headers.py
imap_pydantic_client/helpers/__init__.py
imap_pydantic_client/helpers/calc_timeout.py
imap_pydantic_client/helpers/get_time.py
imap_pydantic_client/helpers/message2email.py
imap_pydantic_client/helpers/takes_argument.py
imap_pydantic_client/helpers/write_dump_mailbox.py
imap_pydantic_client/structs.py
imap_pydantic_client-0.2.0.dist-info/WHEEL
imap_pydantic_client-0.2.0.dist-info/entry_points.txt
imap_pydantic_client-0.2.0.dist-info/METADATA
imap_pydantic_client-0.2.0.dist-info/RECORD
