Metadata-Version: 2.1
Name: imap-pydantic-client
Version: 0.2.0
Summary: 
Home-page: https://github.com/MattiooFR/package_name
License: MIT
Keywords: keyword,another_keyword
Author: alexander.mescheryakov
Author-email: avm@sh-inc.ru
Requires-Python: >=3.10,<4.0
Classifier: License :: OSI Approved :: MIT License
Classifier: Programming Language :: Python :: 3
Classifier: Programming Language :: Python :: 3.10
Classifier: Programming Language :: Python :: 3.11
Requires-Dist: Faker (>=15.3.4,<16.0.0)
Requires-Dist: IMAPClient (>=2.3.1,<3.0.0)
Requires-Dist: email-validator (>=1.3.0,<2.0.0)
Requires-Dist: faker-web (>=0.3.1,<0.4.0)
Requires-Dist: mdgen (>=0.1.10,<0.2.0)
Requires-Dist: pydantic (>=1.10.2,<2.0.0)
Project-URL: Repository, https://github.com/MattiooFR/package_name
